displayfx.py
displayfx-2.2.1.dist-info/METADATA
displayfx-2.2.1.dist-info/WHEEL
displayfx-2.2.1.dist-info/licenses/LICENSE.txt
displayfx-2.2.1.dist-info/RECORD
