Metadata-Version: 2.4
Name: DisplayFX
Version: 2.2.1
Summary: Display progress indicator on CRT screen.
License-Expression: MIT
License-File: LICENSE.txt
Author: Hendrik du Toit
Author-email: hendrik@brightedge.co.za
Maintainer: Hendrik du Toit
Maintainer-email: hendrikdt@citiqprepaid.co.za
Requires-Python: >=3.10
Classifier: Development Status :: 5 - Production/Stable
Classifier: Intended Audience :: Developers
Classifier: Topic :: Software Development
Classifier: License :: OSI Approved :: MIT License
Classifier: Programming Language :: Python :: 3.10
Classifier: Programming Language :: Python :: 3.11
Requires-Dist: beetools (>=5.2.4,<6.0.0)
Project-URL: Homepage, https://github.com/BrightEdgeeServices/DisplayFX
Project-URL: Repository, https://github.com/BrightEdgeeServices/DisplayFX.git
Project-URL: changelog, https://github.com/BrightEdgeeServices/DisplayFX/releases
Project-URL: issues, https://github.com/BrightEdgeeServices/DisplayFX/issues
